geometry1/__init__.py
geometry1/point.py
geometry1/figures/__init__.py
geometry1/figures/line.py
geometry1/figures/triangle.py
geometry1-0.1.dist-info/METADATA
geometry1-0.1.dist-info/WHEEL
geometry1-0.1.dist-info/top_level.txt
geometry1-0.1.dist-info/RECORD
