Metadata-Version: 2.1
Name: geometry1
Version: 0.1
Summary: This package is useful for some geometric calculations
Home-page: UNKNOWN
Author: Nikita Egorov
Author-email: egorovnikita2020@gmail.com
License: UNKNOWN
Platform: UNKNOWN
